oo_cli-0.0.6.dist-info/DESCRIPTION.rst
oo_cli-0.0.6.dist-info/METADATA
oo_cli-0.0.6.dist-info/RECORD
oo_cli-0.0.6.dist-info/WHEEL
oo_cli-0.0.6.dist-info/metadata.json
oo_cli-0.0.6.dist-info/top_level.txt
oocli/__init__.py
oocli/base.py
oocli/echo.py
oocli/entrypoint.py
oocli/exceptions.py
oocli/interpreter.py
